{
  "main": {
    "id": "03e48e08ab411fed",
    "type": "split",
    "children": [
      {
        "id": "36af30d230976c00",
        "type": "tabs",
        "children": [
          {
            "id": "1f2be905c404067d",
            "type": "leaf",
            "state": {
              "type": "markdown",
              "state": {
                "file": "数据库/第一章_数据库概念.md",
                "mode": "preview",
                "source": false
              }
            }
          },
          {
            "id": "bb96da768cd25c30",
            "type": "leaf",
            "state": {
              "type": "markdown",
              "state": {
                "file": "数据库/第二章_关系模型与独立性.md",
                "mode": "source",
                "source": false
              }
            }
          },
          {
            "id": "26b80a7e2665a586",
            "type": "leaf",
            "state": {
              "type": "markdown",
              "state": {
                "file": "数据库/第三章_6设计阶段.md",
                "mode": "source",
                "source": false
              }
            }
          },
          {
            "id": "5f4634a99ad6011a",
            "type": "leaf",
            "state": {
              "type": "markdown",
              "state": {
                "file": "数据库/第七章_DQL_DMLsql.md",
                "mode": "source",
                "source": false
              }
            }
          }
        ],
        "currentTab": 2
      }
    ],
    "direction": "vertical"
  },
  "left": {
    "id": "6d4bb52aa6416c53",
    "type": "split",
    "children": [
      {
        "id": "487c7333c31da16a",
        "type": "tabs",
        "children": [
          {
            "id": "7d7c79a106679c44",
            "type": "leaf",
            "state": {
              "type": "file-explorer",
              "state": {
                "sortOrder": "alphabetical"
              }
            }
          },
          {
            "id": "10e34b0b023a06f2",
            "type": "leaf",
            "state": {
              "type": "search",
              "state": {
                "query": "",
                "matchingCase": false,
                "explainSearch": false,
                "collapseAll": false,
                "extraContext": false,
                "sortOrder": "alphabetical"
              }
            }
          },
          {
            "id": "16a6cc3829a596e9",
            "type": "leaf",
            "state": {
              "type": "starred",
              "state": {}
            }
          }
        ]
      }
    ],
    "direction": "horizontal",
    "width": 374.5
  },
  "right": {
    "id": "fd22a51f8a10e99d",
    "type": "split",
    "children": [
      {
        "id": "17914db88f350a54",
        "type": "tabs",
        "children": [
          {
            "id": "894d029e468cee3b",
            "type": "leaf",
            "state": {
              "type": "backlink",
              "state": {
                "file": "数据库/第三章_6设计阶段.md",
                "collapseAll": true,
                "extraContext": false,
                "sortOrder": "alphabetical",
                "showSearch": false,
                "searchQuery": "",
                "backlinkCollapsed": false,
                "unlinkedCollapsed": false
              }
            }
          },
          {
            "id": "f557a1c291c56739",
            "type": "leaf",
            "state": {
              "type": "outgoing-link",
              "state": {
                "file": "数据库/第三章_6设计阶段.md",
                "linksCollapsed": false,
                "unlinkedCollapsed": true
              }
            }
          },
          {
            "id": "16f16bb983eb882e",
            "type": "leaf",
            "state": {
              "type": "tag",
              "state": {
                "sortOrder": "frequency",
                "useHierarchy": true
              }
            }
          },
          {
            "id": "ba0d3d0b47340067",
            "type": "leaf",
            "state": {
              "type": "outline",
              "state": {
                "file": "数据库/第三章_6设计阶段.md"
              }
            }
          }
        ],
        "currentTab": 3
      }
    ],
    "direction": "horizontal",
    "width": 224.5
  },
  "left-ribbon": {
    "hiddenItems": {
      "canvas:新建白板": false,
      "oz-clear-unused-images:Clear Unused Images": false,
      "switcher:打开快速切换": false,
      "graph:查看关系图谱": false,
      "daily-notes:打开/创建今天的日记": false,
      "templates:插入模板": false,
      "command-palette:打开命令面板": false
    }
  },
  "active": "26b80a7e2665a586",
  "lastOpenFiles": [
    "数据库/img/Pasted image 20230315235320.png",
    "数据库/img/Pasted image 20230315235059.png",
    "数据库/img/Pasted image 20230315234718.png",
    "数据库/img/Pasted image 20230315234619.png",
    "数据库/img/Pasted image 20230315234428.png",
    "数据库/img/Pasted image 20230315234330.png",
    "数据库/img/Pasted image 20230315233152.png",
    "数据库/第二章_关系模型与独立性.md",
    "数据库/img/Pasted image 20230315233002.png",
    "数据库/第一章_数据库概念.md",
    "数据库/第三章_6设计阶段.md",
    "数据库/img/Pasted image 20230315232757.png",
    "数据库/img/Pasted image 20230315232706.png",
    "数据库/img/Pasted image 20230315232612.png",
    "数据库/第七章_DQL_DMLsql.md",
    "数据库/第八章_DML.md",
    "数据库/第四章_范式.md",
    "数据库/第五章_安全性DCL.md",
    "数据库/第六章_并发.md",
    "math/第十一课_多元函数与微分.pdf",
    "math/第十课_空间解析几何与向量.pdf",
    "math/第九课_分部积分求定积分.pdf",
    "math/多元函数与微分.pdf",
    "math/空 间 解 析 几 何 与 向 量.pdf",
    "math/分 部 积 分 求 定 积 分.pdf",
    "Day Planners/Day Planner-20230315.md",
    "软件测试/第一章.md",
    "Day Planners/Day Planner-20230314.md",
    "Day Planners",
    "Day Planners/Day Planner-20230209.md",
    "Day Planners/Day Planner-20230127.md",
    "c语言/位操作.md",
    "c语言/其他.md",
    "c语言/const关键词.md",
    "c语言/static关键字.md",
    "c语言/指针.md",
    "c语言/函数.md",
    "c语言/数组.md",
    "c语言/数据类型.md",
    "c语言/宏定义.md",
    "c语言/专升本_做题.md",
    "c语言/专升本_细枝末节.md",
    "c语言/内存分区.md",
    "math/第八课_定积分.pdf",
    "math/第六课_不定积分.pdf",
    "math/第七课_不定积分二.pdf"
  ]
}